package_anushree56/__init__.py
package_anushree56/hello_ac.py
package_anushree56/version.py
package_anushree56-0.0.1.dist-info/LICENSE
package_anushree56-0.0.1.dist-info/METADATA
package_anushree56-0.0.1.dist-info/WHEEL
package_anushree56-0.0.1.dist-info/top_level.txt
package_anushree56-0.0.1.dist-info/RECORD
