Metadata-Version: 2.1
Name: package_anushree56
Version: 0.0.1
Summary: A small example package just for testing
Author-email: Anushree <anushree56.sxc@gmail.com>
Project-URL: Homepage, https://github.com/pypa/sampleproject
Project-URL: Issues, https://github.com/pypa/sampleproject/issues
Keywords: greet,test,ai,ml
Classifier: Programming Language :: Python :: 3
Classifier: License :: OSI Approved :: MIT License
Classifier: Operating System :: OS Independent
Requires-Python: >=3.8
License-File: LICENSE
Requires-Dist: opencv-contrib-python
